[{"exportedComponentClass": "Modelica.Mechanics.Translational.Components.Damper", "components": [{"comment": "Linear 1D translational damper", "parameters": [{"fullName": "Real", "modifiers": {"start": "0", "quantity": "\"TranslationalDampingConstant\"", "unit": "\"N.s/m\"", "min": "0"}, "name": "d", "value": "", "description": "Damping constant"}], "imports": [], "connectors": [], "extends": [{"fullName": "Modelica.Mechanics.Translational.Interfaces.PartialCompliantWithRelativeStates", "modifiers": {}, "redeclare_parameters": [], "parameters": []}, {"fullName": "Modelica.Thermal.HeatTransfer.Interfaces.PartialElementaryConditionalHeatPortWithoutT", "modifiers": {}, "redeclare_parameters": [], "parameters": []}], "fullName": "Modelica.Mechanics.Translational.Components.Damper", "packages": [], "redeclare_parameters": []}, {"comment": "Base model for the compliant connection of two translational 1-dim. shaft flanges where the relative position and relative velocities are used as states", "parameters": [{"fullName": "StateSelect", "modifiers": {}, "name": "stateSelect", "value": "StateSelect.prefer", "description": "Priority to use phi_rel and w_rel as states"}, {"fullName": "Real", "modifiers": {"quantity": "\"Length\"", "unit": "\"m\"", "min": "0"}, "name": "s_nominal", "value": 0.0001, "description": "Nominal value of s_rel (used for scaling)"}], "imports": [], "connectors": [{"fullName": "Modelica.Mechanics.Translational.Interfaces.Flange_a", "modifiers": {}, "name": "flange_a", "parameters": [], "redeclare_parameters": []}, {"fullName": "Modelica.Mechanics.Translational.Interfaces.Flange_b", "modifiers": {}, "name": "flange_b", "parameters": [], "redeclare_parameters": []}], "extends": [], "fullName": "Modelica.Mechanics.Translational.Interfaces.PartialCompliantWithRelativeStates", "packages": [], "redeclare_parameters": []}, {"comment": "Partial model to include a conditional HeatPort in order to dissipate losses, used for textual modeling, i.e., for elementary models", "parameters": [{"fullName": "Boolean", "modifiers": {}, "name": "useHeatPort", "value": false, "description": "=true, if heatPort is enabled"}], "imports": [], "connectors": [{"fullName": "Modelica.Thermal.HeatTransfer.Interfaces.HeatPort_a", "modifiers": {"modifications": "public", "Q_flow": "-lossPower"}, "name": "heatPort", "parameters": [], "redeclare_parameters": []}], "extends": [], "fullName": "Modelica.Thermal.HeatTransfer.Interfaces.PartialElementaryConditionalHeatPortWithoutT", "packages": [], "redeclare_parameters": []}]}]